{
  "_class": "symbolInstance",
  "booleanOperation": -1,
  "clippingMaskMode": 0,
  "do_objectID": "2AF4B917-D72A-43CD-88F1-8F60A01F8471",
  "exportOptions": {
    "_class": "exportOptions",
    "do_objectID": "34AB0592-0E4B-4799-AE7C-A92374F70082",
    "exportFormats": [
    ],
    "includedLayerIds": [
    ],
    "layerOptions": 0,
    "shouldTrim": false
  },
  "frame": {
    "_class": "rect",
    "constrainProportions": false,
    "do_objectID": "A2D3C8E4-CF43-4418-99E8-293413D2FB5B",
    "height": 20,
    "width": 134,
    "x": 823,
    "y": 10
  },
  "hasClippingMask": false,
  "horizontalSpacing": 0,
  "isFixedToViewport": false,
  "isFlippedHorizontal": false,
  "isFlippedVertical": false,
  "isLocked": false,
  "isVisible": true,
  "layerListExpandedType": 0,
  "name": "CheckBox/checked disable备份",
  "nameIsFixed": false,
  "overrideValues": [
  ],
  "resizingConstraint": 63,
  "resizingType": 0,
  "rotation": 0,
  "scale": 1,
  "shouldBreakMaskChain": false,
  "style": {
    "_class": "style",
    "do_objectID": "F93765A2-00B2-4984-BEE1-C922AD01CE5B",
    "endMarkerType": 0,
    "miterLimit": 10,
    "startMarkerType": 0,
    "windingRule": 1
  },
  "symbolID": "5DD3F02A-E52F-4111-BC8C-EDF4D61C2D14",
  "verticalSpacing": 0
}